asyncUnittest/__init__.py
asyncUnittest/async_unittest.py
asyncUnittest-1.5.6.dist-info/LICENSE
asyncUnittest-1.5.6.dist-info/METADATA
asyncUnittest-1.5.6.dist-info/WHEEL
asyncUnittest-1.5.6.dist-info/top_level.txt
asyncUnittest-1.5.6.dist-info/RECORD
