Metadata-Version: 2.1
Name: asyncUnittest
Version: 1.5.6
Summary: Fully asynchronous unit test
Home-page: https://github.com/monk-after-90s/asyncUnittest.git
Author: Antas
License: MIT
Platform: UNKNOWN
Classifier: Programming Language :: Python :: 3
Classifier: License :: OSI Approved :: MIT License
Classifier: Operating System :: OS Independent
Requires-Python: >=3.7
License-File: LICENSE
Requires-Dist: beeprint
Requires-Dist: loguru
